nowtime/__init__.py
nowtime/main.py
nowtime-0.1.4.dist-info/METADATA
nowtime-0.1.4.dist-info/WHEEL
nowtime-0.1.4.dist-info/top_level.txt
nowtime-0.1.4.dist-info/RECORD
