Metadata-Version: 2.1
Name: nowtime
Version: 0.1.4
Summary: Default template for PDM package
Author-email: hun0219 <gsw98000@gmail.com>
License: MIT
Requires-Python: ==3.11.*
Requires-Dist: pytz>=2024.2
